grplist/PROJECT.txt
grplist/__init__.py
grplist/grplist.py
grplist-0.1.4.dist-info/LICENSE
grplist-0.1.4.dist-info/METADATA
grplist-0.1.4.dist-info/WHEEL
grplist-0.1.4.dist-info/top_level.txt
grplist-0.1.4.dist-info/RECORD
