Metadata-Version: 2.1
Name: grplist
Version: 0.1.4
Summary: Groups list items using a compare function
Home-page: https://github.com/wheresjames/grplist
Author: Robert Umbehant
Author-email: grplist@wheresjames.com
License: MIT
Platform: UNKNOWN
